reg_stat_inference/__init__.py
reg_stat_inference/main.py
reg_stat_inference-0.1.9.dist-info/METADATA
reg_stat_inference-0.1.9.dist-info/WHEEL
reg_stat_inference-0.1.9.dist-info/RECORD
