Metadata-Version: 2.1
Name: reg-stat-inference
Version: 0.1.9
Summary: Treat multicollinearity and non-significant variables from your statsmodels linear and logistic regressions
Author: Dirceu Silva
Author-email: ddasilvajunior@vio.com
Requires-Python: >=3.7,<4.0
Classifier: Programming Language :: Python :: 3
Classifier: Programming Language :: Python :: 3.7
Classifier: Programming Language :: Python :: 3.8
Classifier: Programming Language :: Python :: 3.9
Classifier: Programming Language :: Python :: 3.10
Classifier: Programming Language :: Python :: 3.11
Requires-Dist: numpy
Requires-Dist: pandas
Requires-Dist: statsmodels
